maajik/__init__.py
maajik/system.py
maajik/dictionaries/briefs.json
maajik/dictionaries/commands.json
maajik/dictionaries/main.json
maajik/dictionaries/punctuation.json
plover_maajik-1.0.0b2.dist-info/LICENSE
plover_maajik-1.0.0b2.dist-info/METADATA
plover_maajik-1.0.0b2.dist-info/WHEEL
plover_maajik-1.0.0b2.dist-info/entry_points.txt
plover_maajik-1.0.0b2.dist-info/top_level.txt
plover_maajik-1.0.0b2.dist-info/RECORD
