Metadata-Version: 2.1
Name: plover-maajik
Version: 1.0.0b2
Summary: Cantonese steno system plugin for Plover
Author: Samuel Lo
Author-email: Sammi de Guzman <sammi@sammdot.ca>
License: Copyright (c) 2022 Sammi de Guzman, Samuel Lo, and MaaJik contributors        
Project-URL: repository, https://github.com/sammdot/plover-maajik
Project-URL: homepage, https://github.com/sammdot/plover-maajik
Keywords: plover,plover_plugin
Classifier: Programming Language :: Python :: 3.7
Classifier: Programming Language :: Python :: 3.8
Classifier: Programming Language :: Python :: 3.9
Classifier: Programming Language :: Python :: 3.10
Requires-Python: >=3.7
License-File: LICENSE
Requires-Dist: plover (>=4.0.0.dev11)
